{
  "result": {
    "client_name": {
      "answer": "מי שבע - תאגיד אזורי למים וביוב בע\"מ",
      "details": "שם הלקוח מופיע בתחילת הטקסט ובמספר מקומות נוספים.",
      "source": "עמוד 2, פסקה ראשונה",
      "score": 5
    },
    "tender_name": {
      "answer": "מתן שירותי תמיכה DBA פרו אקטיביים לניטור ואחזקת בסיסי מידע בסביבת SQL SER",
      "details": "שם המכרז כפי שמופיע בכותרת המכרז",
      "source": "עמוד 1, פסקה ראשונה",
      "score": 5
    },
    "threshold_conditions": {
      "answer": "רשאים להשתתף בהליך מציעים העומדים במועד הגשת הצעותיהם בכל תנאי הסף ותנאי העמידה בהליך המפורטים במסמך ההוראות למשתתפים, הכול כמפורט ובכפוף לאמור במסמכי המכרז.",
      "details": "תנאי הסף מפורטים במסמך ההוראות למשתתפים ומצוינים בטקסט.",
      "source": "עמוד 2, פסקה שנייה",
      "score": 5
    },
    "contract_period": {
      "answer": "תקופת ההתקשרות המקורית היא שנתיים (24 חודשים) ממועד החתימה על ההסכם, עם תקופת ניסיון של שלושה חודשים ראשונים; לחברה תהיה אופציה להאריך את ההתקשרות ב-3 תקופות נוספות בנות 12 חודשים או חלק מהם.",
      "details": "התקופה מפורטת בסעיף 5.3 ו-5.4 של המכרז.",
      "source": "עמוד 1, פסקאות 5.3 ו-5.4",
      "score": 5
    },
    "evaluation_method": {
      "answer": "חישוב משוקלל ומתן ציון כולל למרכיבי ההצעה: איכות (60%) ומחיר (40%). מרכיב המחיר מבוסס על אחוז הנחה בין 0-15%, כאשר ההצעה עם שיעור ההנחה הגבוה ביותר מקבלת 40 נקודות, והיתר נקודות יחסיות. מרכיב האיכות מהווה 60% מהציון הכולל ומבוסס על נוסחה בהתאם לפרמטרים בטבלה.",
      "details": "מתואר בסעיפים 11.2, 11.4, כולל משקולות, נוסחאות וחישוב נקודות.",
      "source": "עמוד 18, פסקאות 11.2, 11.4",
      "score": 5
    },
    "bid_guarantee": {
      "answer": "ערבות בנקאית אוטונומית בסך 10,000 ₪ (עשרת אלפים שקלים) בנוסח המצ\"ב כטופס 3 למסמכי המכרז",
      "details": "סכום ערבות ההגשה מפורט במפורש עם דרישה לערבות בנקאית אוטונומית.",
      "source": "עמוד 7, פסקה אחרונה",
      "score": 5
    },
    "idea_author": {
      "answer": "",
      "details": "לא נמצא מידע על מחבר הרעיון או היוזם",
      "source": "לא נמצא",
      "score": 0
    }
  }
}